{
  "format_version": "1.21.10",
  "minecraft:item": {
    "description": {
      "identifier": "vsconw:blacksteel_rapier",
      "category": "equipment"
    },
    "minecraft:enchantable": {
        "value": 27,
        "slot": "sword"
      },
    "components": {
      "minecraft:icon": {
        "texture": "blacksteel_rapier"
      },
      "minecraft:damage": 9999,
      "minecraft:weapon": {
        "damage": 7
      },
      "minecraft:display_name": {
        "value": "§0黒鋼のレイピア"
      }
    }
  }
}
